Workbook

Sheet Sensitivity
A1: SENSITIVITY ANALYSIS - VALUE PER SHARE
A3: WACC / Growth | B3: 0.02 | C3: 0.025 | D3: 0.03 | E3: 0.035 | F3: 0.04
A4: 0.1 | B4: =Valuation!B24 -> 31.353053 | C4: =Valuation!B24 -> 31.353053 | D4: =Valuation!B24 -> 31.353053 | E4: =Valuation!B24 -> 31.353053 | F4: =Valuation!B24 -> 31.353053
A5: 0.105 | B5: =Valuation!B24 -> 31.353053 | C5: =Valuation!B24 -> 31.353053 | D5: =Valuation!B24 -> 31.353053 | E5: =Valuation!B24 -> 31.353053 | F5: =Valuation!B24 -> 31.353053
A6: 0.11 | B6: =Valuation!B24 -> 31.353053 | C6: =Valuation!B24 -> 31.353053 | D6: =Valuation!B24 -> 31.353053 | E6: =Valuation!B24 -> 31.353053 | F6: =Valuation!B24 -> 31.353053
A7: 0.115 | B7: =Valuation!B24 -> 31.353053 | C7: =Valuation!B24 -> 31.353053 | D7: =Valuation!B24 -> 31.353053 | E7: =Valuation!B24 -> 31.353053 | F7: =Valuation!B24 -> 31.353053
A8: 0.12 | B8: =Valuation!B24 -> 31.353053 | C8: =Valuation!B24 -> 31.353053 | D8: =Valuation!B24 -> 31.353053 | E8: =Valuation!B24 -> 31.353053 | F8: =Valuation!B24 -> 31.353053
A10: Key Drivers Sensitivity
A11: Variable | B11: Base Case | C11: 0.1 | D11: -0.1 | E11: Impact on Value/Share
A12: Revenue Growth | B12: =Input_Assumptions!B13 -> 0.15 | C12: =B12*1.1 -> 0.165 | D12: =B12*0.9 -> 0.135 | E12: =Valuation!B24 -> 31.353053
A13: WACC | B13: =Discount_Rate!B20 -> 0.10038462 | C13: =B13*1.1 -> 0.11042308 | D13: =B13*0.9 -> 0.090346154 | E13: =Valuation!B24 -> 31.353053
A14: Terminal Growth | B14: =Input_Assumptions!B34 -> 0.03 | C14: =B14*1.1 -> 0.033 | D14: =B14*0.9 -> 0.027 | E14: =Valuation!B24 -> 31.353053

Sheet Valuation
A1: DISCOUNTED CASH FLOW VALUATION
A3: Year | B3: 2024 | C3: 2025 | D3: 2026 | E3: 2027 | F3: 2028
A5: Free Cash Flow | B5: =FCF_Calculation!B10 -> 865000 | C5: =FCF_Calculation!C10 -> 1994750 | D5: =FCF_Calculation!D10 -> 2293962.5 | E5: =FCF_Calculation!E10 -> 2638056.9 | F5: =FCF_Calculation!F10 -> 3033765.4
A6: Discount Factor | B6: =Discount_Rate!B24 -> 0.90877316 | C6: =Discount_Rate!C24 -> 0.82586865 | D6: =Discount_Rate!D24 -> 0.75052726 | E6: =Discount_Rate!E24 -> 0.68205903 | F6: =Discount_Rate!F24 -> 0.61983693
A7: Present Value of FCF | B7: =B5*B6 -> 786088.78 | C7: =C5*C6 -> 1647401.5 | D7: =D5*D6 -> 1721681.4 | E7: =E5*E6 -> 1799310.5 | F7: =F5*F6 -> 1880439.8
A9: Terminal Value Calculation
A10: Terminal FCF (2029) | B10: =F5*(1+Input_Assumptions!B34) -> 3124778.4
A11: Terminal Growth Rate: | B11: =Input_Assumptions!B34 -> 0.03
A12: WACC: | B12: =Discount_Rate!B20 -> 0.10038462
A13: Terminal Value (at end of 2028) | B13: =B10/(B12-B11) -> 44395758
A14: Present Value of Terminal Value | B14: =B13*F6 -> 27518131
A16: Valuation Summary
A17: Sum of PV of FCF (2024-2028) | B17: =SUM(B7:F7) -> 7834922
A18: PV of Terminal Value | B18: =B14 -> 27518131
A19: Enterprise Value | B19: =B17+B18 -> 35353053
A20: Plus: Cash & Equivalents | B20: =1000000 -> 1000000
A21: Less: Debt | B21: =5000000 -> 5000000
A22: Equity Value | B22: =B19+B20-B21 -> 31353053
A23: Shares Outstanding | B23: =1000000 -> 1000000
A24: Value per Share | B24: =B22/B23 -> 31.353053

Sheet Discount_Rate
A1: WEIGHTED AVERAGE COST OF CAPITAL (WACC) CALCULATION
A3: Cost of Equity (CAPM)
A4: Risk-Free Rate: | B4: =Input_Assumptions!B27 -> 0.045
A5: Market Risk Premium: | B5: =Input_Assumptions!B28 -> 0.06
A6: Beta: | B6: =Input_Assumptions!B29 -> 1.2
A7: Cost of Equity: | B7: =B4+B6*B5 -> 0.117
A9: Cost of Debt
A10: Pre-tax Cost of Debt: | B10: =Input_Assumptions!B30 -> 0.06
A11: Tax Rate: | B11: =Input_Assumptions!B20 -> 0.25
A12: After-tax Cost of Debt: | B12: =B10*(1-B11) -> 0.045
A14: Capital Structure
A15: Debt/Equity Ratio: | B15: =Input_Assumptions!B31 -> 0.3
A16: Weight of Debt: | B16: =B15/(1+B15) -> 0.23076923
A17: Weight of Equity: | B17: =1/(1+B15) -> 0.76923077
A19: WACC Calculation
A20: WACC: | B20: =B17*B7+B16*B12 -> 0.10038462
A22: Discount Factors
A23: Year | B23: 1 | C23: 2 | D23: 3 | E23: 4 | F23: 5
A24: Discount Factor | B24: =1/(1+B20)^B23 -> 0.90877316 | C24: =1/(1+B20)^C23 -> 0.82586865 | D24: =1/(1+B20)^D23 -> 0.75052726 | E24: =1/(1+B20)^E23 -> 0.68205903 | F24: =1/(1+B20)^F23 -> 0.61983693

Sheet FCF_Calculation
A1: FREE CASH FLOW (FCF) CALCULATION
A3: Year | B3: 2024 | C3: 2025 | D3: 2026 | E3: 2027 | F3: 2028
A5: NOPAT | B5: =Expenses!B10 -> 2505000 | C5: =Expenses!C10 -> 2880750 | D5: =Expenses!D10 -> 3312862.5 | E5: =Expenses!E10 -> 3809791.9 | F5: =Expenses!F10 -> 4381260.7
A6: Add: Depreciation | B6: =Expenses!B6 -> 160000 | C6: =Expenses!C6 -> 184000 | D6: =Expenses!D6 -> 211600 | E6: =Expenses!E6 -> 243340 | F6: =Expenses!F6 -> 279841
A7: Less: Capital Expenditure | B7: =Expenses!B8 -> 800000 | C7: =Expenses!C8 -> 920000 | D7: =Expenses!D8 -> 1058000 | E7: =Expenses!E8 -> 1216700 | F7: =Expenses!F8 -> 1399205
A8: Less: Change in Working Capital | B8: =Revenue_Projections!B5*Input_Assumptions!B24 -> 1000000 | C8: =(Revenue_Projections!C5-Revenue_Projections!B5)*Input_Assumptions!B24 -> 150000 | D8: =(Revenue_Projections!D5-Revenue_Projections!C5)*Input_Assumptions!B24 -> 172500 | E8: =(Revenue_Projections!E5-Revenue_Projections!D5)*Input_Assumptions!B24 -> 198375 | F8: =(Revenue_Projections!F5-Revenue_Projections!E5)*Input_Assumptions!B24 -> 228131.25
A10: Free Cash Flow (FCF) | B10: =B5+B6-B7-B8 -> 865000 | C10: =C5+C6-C7-C8 -> 1994750 | D10: =D5+D6-D7-D8 -> 2293962.5 | E10: =E5+E6-E7-E8 -> 2638056.9 | F10: =F5+F6-F7-F8 -> 3033765.4
A12: Cumulative FCF | B12: =B10 -> 865000 | C12: =B12+C10 -> 2859750 | D12: =C12+D10 -> 5153712.5 | E12: =D12+E10 -> 7791769.4 | F12: =E12+F10 -> 10825535

Sheet Expenses
A1: OPERATING EXPENSES & EBITDA
A3: Year | B3: 2024 | C3: 2025 | D3: 2026 | E3: 2027 | F3: 2028
A5: Operating Expenses ($) | B5: =Revenue_Projections!B5*Input_Assumptions!B18 -> 2500000 | C5: =Revenue_Projections!C5*Input_Assumptions!B18 -> 2875000 | D5: =Revenue_Projections!D5*Input_Assumptions!B18 -> 3306250 | E5: =Revenue_Projections!E5*Input_Assumptions!B18 -> 3802187.5 | F5: =Revenue_Projections!F5*Input_Assumptions!B18 -> 4372515.6
A6: Depreciation ($) | B6: =Input_Assumptions!B19*B8 -> 160000 | C6: =Input_Assumptions!B19*C8 -> 184000 | D6: =Input_Assumptions!B19*D8 -> 211600 | E6: =Input_Assumptions!B19*E8 -> 243340 | F6: =Input_Assumptions!B19*F8 -> 279841
A7: EBIT | B7: =Revenue_Projections!B9-B5-B6 -> 3340000 | C7: =Revenue_Projections!C9-C5-C6 -> 3841000 | D7: =Revenue_Projections!D9-D5-D6 -> 4417150 | E7: =Revenue_Projections!E9-E5-E6 -> 5079722.5 | F7: =Revenue_Projections!F9-F5-F6 -> 5841680.9
A8: Capital Expenditure (Capex) | B8: =Revenue_Projections!B5*Input_Assumptions!B23 -> 800000 | C8: =Revenue_Projections!C5*Input_Assumptions!B23 -> 920000 | D8: =Revenue_Projections!D5*Input_Assumptions!B23 -> 1058000 | E8: =Revenue_Projections!E5*Input_Assumptions!B23 -> 1216700 | F8: =Revenue_Projections!F5*Input_Assumptions!B23 -> 1399205
A9: Taxes | B9: =B7*Input_Assumptions!B20 -> 835000 | C9: =C7*Input_Assumptions!B20 -> 960250 | D9: =D7*Input_Assumptions!B20 -> 1104287.5 | E9: =E7*Input_Assumptions!B20 -> 1269930.6 | F9: =F7*Input_Assumptions!B20 -> 1460420.2
A10: NOPAT (Net Operating Profit After Tax) | B10: =B7-B9 -> 2505000 | C10: =C7-C9 -> 2880750 | D10: =D7-D9 -> 3312862.5 | E10: =E7-E9 -> 3809791.9 | F10: =F7-F9 -> 4381260.7

Sheet Revenue_Projections
A1: REVENUE PROJECTIONS (5-YEAR FORECAST)
A3: Year | B3: 2024 | C3: 2025 | D3: 2026 | E3: 2027 | F3: 2028
A5: Revenue ($) | B5: =Input_Assumptions!B12 -> 10000000 | C5: =B5*(1+Input_Assumptions!B13) -> 11500000 | D5: =C5*(1+Input_Assumptions!B13) -> 13225000 | E5: =D5*(1+Input_Assumptions!B13) -> 15208750 | F5: =E5*(1+Input_Assumptions!B13) -> 17490062
A6: Growth Rate | B6: - | C6: =Input_Assumptions!B13 -> 0.15 | D6: =Input_Assumptions!B13 -> 0.15 | E6: =Input_Assumptions!B13 -> 0.15 | F6: =Input_Assumptions!B13 -> 0.15
A8: Cost of Goods Sold (COGS) | B8: =B5*Input_Assumptions!B17 -> 4000000 | C8: =C5*Input_Assumptions!B17 -> 4600000 | D8: =D5*Input_Assumptions!B17 -> 5290000 | E8: =E5*Input_Assumptions!B17 -> 6083500 | F8: =F5*Input_Assumptions!B17 -> 6996025
A9: Gross Profit | B9: =B5-B8 -> 6000000 | C9: =C5-C8 -> 6900000 | D9: =D5-D8 -> 7935000 | E9: =E5-E8 -> 9125250 | F9: =F5-F8 -> 10494037
A10: Gross Margin | B10: =B9/B5 -> 0.6 | C10: =C9/C5 -> 0.6 | D10: =D9/D5 -> 0.6 | E10: =E9/E5 -> 0.6 | F10: =F9/F5 -> 0.6

Sheet Input_Assumptions
A1: DISCOUNTED CASH FLOW (DCF) MODEL - INPUT ASSUMPTIONS
A3: Company Information
A4: Company Name: | B4: Sample Company Inc.
A5: Industry: | B5: Technology
A6: Base Year: | B6: 2024
A8: Forecast Period
A9: Forecast Years: | B9: 5
A11: Revenue Assumptions
A12: Current Revenue ($): | B12: 10000000
A13: Revenue Growth Rate (%): | B13: 0.15
A14: Terminal Growth Rate (%): | B14: 0.03
A16: Expense Assumptions
A17: COGS (% of Revenue): | B17: 0.4
A18: Operating Expenses (% of Revenue): | B18: 0.25
A19: Depreciation (% of Capex): | B19: 0.2
A20: Tax Rate (%): | B20: 0.25
A22: Capital Expenditure
A23: Capex (% of Revenue): | B23: 0.08
A24: Working Capital (% of Revenue): | B24: 0.1
A26: Discount Rate Assumptions
A27: Risk-Free Rate (%): | B27: 0.045
A28: Market Risk Premium (%): | B28: 0.06
A29: Beta: | B29: 1.2
A30: Cost of Debt (%): | B30: 0.06
A31: Debt/Equity Ratio: | B31: 0.3
A33: Terminal Value Assumptions
A34: Terminal Growth Rate (%): | B34: 0.03
A35: Exit Multiple (EV/EBITDA): | B35: 8

Sheet Summary
A1: DISCOUNTED CASH FLOW (DCF) MODEL - EXECUTIVE SUMMARY
A3: Valuation Results
A4: Enterprise Value: | B4: See Valuation Sheet
A5: Equity Value: | B5: See Valuation Sheet
A6: Value per Share: | B6: See Valuation Sheet
A8: Key Financial Metrics
A9: Current Revenue: | B9: See Input_Assumptions
A10: 5-Year Revenue CAGR: | B10: See Input_Assumptions
A11: Terminal Growth Rate: | B11: See Input_Assumptions
A12: WACC: | B12: See Discount_Rate
A14: Model Navigation
A15: 1. Input_Assumptions - Key model parameters
A16: 2. Revenue_Projections - 5-year revenue forecast
A17: 3. Expenses - Operating expenses & EBITDA
A18: 4. FCF_Calculation - Free cash flow derivation
A19: 5. Discount_Rate - WACC calculation
A20: 6. Valuation - DCF valuation results
A21: 7. Sensitivity - Sensitivity analysis
A23: Instructions
A24: 1. Update assumptions in Input_Assumptions sheet
A25: 2. Review revenue projections in Revenue_Projections
A26: 3. Check valuation results in Valuation sheet
... A30: Copyright © 2024 MICA
